FinRatioAnalysis/FinRatioAnalysis.py
FinRatioAnalysis/__init__.py
FinRatioAnalysis-0.0.7.dist-info/LICENCE
FinRatioAnalysis-0.0.7.dist-info/METADATA
FinRatioAnalysis-0.0.7.dist-info/WHEEL
FinRatioAnalysis-0.0.7.dist-info/top_level.txt
FinRatioAnalysis-0.0.7.dist-info/RECORD
