Metadata-Version: 2.1
Name: FinRatioAnalysis
Version: 0.0.7
Summary: Quantitative Finance Ratio Analysis
Home-page: https://github.com/lorenzo1285
Author: Lorenzo Cárdenas Cárdenas
Author-email: <lorenzo_cardenas@msn.com>
License: MIT
Keywords: python,finance,quantitative analysis,fundamental analysis,portfolio
Platform: UNKNOWN
Classifier: Development Status :: 1 - Planning
Classifier: Intended Audience :: Developers
Classifier: Programming Language :: Python :: 3
Classifier: Operating System :: Unix
Classifier: Operating System :: MacOS :: MacOS X
Classifier: Operating System :: Microsoft :: Windows
Requires-Python: >=3.7
License-File: LICENCE
Requires-Dist: yfinance
Requires-Dist: numpy
Requires-Dist: pandas
Requires-Dist: pandas-datareader
Requires-Dist: plotly
